{
    "views": [
        {
            "view": "button",
            "id": "button_1",
            "start_percent": "15",
            "top_percent": "88",
            "end_percent": "37",
            "bottom_percent": "94"
        },
        {
            "view": "button",
            "id": "button_2",
            "start_percent": "57",
            "top_percent": "88",
            "end_percent": "81",
            "bottom_percent": "96"
        },
        {
            "view": "editText",
            "id": "editText_1",
            "start_percent": "20",
            "top_percent": "54",
            "end_percent": "80",
            "bottom_percent": "69"
        },
        {
            "view": "editText",
            "id": "editText_2",
            "start_percent": "20",
            "top_percent": "33",
            "end_percent": "80",
            "bottom_percent": "45"
        },
        {
            "view": "imageView",
            "id": "imageView_1",
            "start_percent": "41",
            "top_percent": "4",
            "end_percent": "64",
            "bottom_percent": "24"
        }
    ]
}
